alibabacloud_dds20151201/__init__.py
alibabacloud_dds20151201/client.py
alibabacloud_dds20151201/models/__init__.py
alibabacloud_dds20151201/models/_allocate_dbinstance_srv_network_address_request.py
alibabacloud_dds20151201/models/_allocate_dbinstance_srv_network_address_response.py
alibabacloud_dds20151201/models/_allocate_dbinstance_srv_network_address_response_body.py
alibabacloud_dds20151201/models/_allocate_node_private_network_address_request.py
alibabacloud_dds20151201/models/_allocate_node_private_network_address_response.py
alibabacloud_dds20151201/models/_allocate_node_private_network_address_response_body.py
alibabacloud_dds20151201/models/_allocate_public_network_address_request.py
alibabacloud_dds20151201/models/_allocate_public_network_address_response.py
alibabacloud_dds20151201/models/_allocate_public_network_address_response_body.py
alibabacloud_dds20151201/models/_cancel_active_operation_tasks_request.py
alibabacloud_dds20151201/models/_cancel_active_operation_tasks_response.py
alibabacloud_dds20151201/models/_cancel_active_operation_tasks_response_body.py
alibabacloud_dds20151201/models/_check_cloud_resource_authorized_request.py
alibabacloud_dds20151201/models/_check_cloud_resource_authorized_response.py
alibabacloud_dds20151201/models/_check_cloud_resource_authorized_response_body.py
alibabacloud_dds20151201/models/_check_recovery_condition_request.py
alibabacloud_dds20151201/models/_check_recovery_condition_response.py
alibabacloud_dds20151201/models/_check_recovery_condition_response_body.py
alibabacloud_dds20151201/models/_check_service_linked_role_request.py
alibabacloud_dds20151201/models/_check_service_linked_role_response.py
alibabacloud_dds20151201/models/_check_service_linked_role_response_body.py
alibabacloud_dds20151201/models/_create_account_request.py
alibabacloud_dds20151201/models/_create_account_response.py
alibabacloud_dds20151201/models/_create_account_response_body.py
alibabacloud_dds20151201/models/_create_backup_request.py
alibabacloud_dds20151201-9.3.0.dist-info/LICENSE
alibabacloud_dds20151201-9.3.0.dist-info/METADATA
alibabacloud_dds20151201-9.3.0.dist-info/WHEEL
alibabacloud_dds20151201-9.3.0.dist-info/top_level.txt
alibabacloud_dds20151201-9.3.0.dist-info/RECORD
